{
    "top_dezenas": [
        9,
        7,
        11,
        14,
        21,
        12,
        19,
        20,
        17,
        8,
        18,
        13,
        6,
        16,
        25
    ],
    "frequencia_dezenas": {
        "6": 1239,
        "7": 1288,
        "8": 1249,
        "9": 1307,
        "11": 1288,
        "12": 1272,
        "13": 1244,
        "14": 1284,
        "16": 1225,
        "17": 1253,
        "18": 1248,
        "19": 1265,
        "20": 1260,
        "21": 1283,
        "25": 1156,
        "4": 775,
        "10": 827,
        "22": 760,
        "23": 732,
        "15": 786,
        "1": 782,
        "3": 768,
        "5": 798,
        "24": 711,
        "2": 780
    },
    "media_pares": 7.13,
    "media_soma": 199.01,
    "total_jogos": 1772
}